<?xml version='1.0' encoding='UTF-8' ?><PLANTASHERBACEASELENHOSAS_CAMPSAV_05MAI23 id="PLANTASHERBACEASELENHOSAS_CAMPSAV_05MAI23" version="1" xmlns:h="http://www.w3.org/1999/xhtml" xmlns:jr="http://openrosa.org/javarosa" xmlns:xsd="http://www.w3.org/2001/XMLSchema" xmlns:ev="http://www.w3.org/2001/xml-events" xmlns:orx="http://openrosa.org/xforms" xmlns:odk="http://www.opendatakit.org/xforms"><starttime>2023-10-27T08:51:43.989-04:00</starttime><deviceid>collect:Q2PfsuTvEdUyeqn5</deviceid><devicephonenum /><inicio /><uc>143</uc><estacao_amostral>382</estacao_amostral><unidade_amostral>1889</unidade_amostral><data_hora><data>2023-10-27</data><hora>10:53:14.147-04:00</hora></data_hora><coletor><icone_colaborador /><cpf>12544903708</cpf><nome>Ronald</nome></coletor><form_veg>savanica</form_veg><impact_manejo_uso><impacto_manejo_uso>não</impacto_manejo_uso></impact_manejo_uso><amostragem><ponto_inicio_transecto>-12.3084594 -63.3872868 183.6981201171875 4.472</ponto_inicio_transecto><foto_ponto_inicial>1698412327095.jpg</foto_ponto_inicial><num_placa>1131</num_placa><modulo>basico</modulo><registro_count>101</registro_count><registro><ponto_amostral>1</ponto_amostral><ponto_metro>0</ponto_metro><ponto_metro_count /><tipo_forma_vida>seca_morta serrapilheira nativa</tipo_forma_vida><forma_vida_nativa>graminoide</forma_vida_nativa><forma_vida_seca_morta>graminoide</forma_vida_seca_morta><uuid>995b7e8d-51dc-4639-b56d-76be951ae64c</uuid></registro><registro><ponto_amostral>2</ponto_amostral><ponto_metro>0.5</ponto_metro><ponto_metro_count /><tipo_forma_vida>serrapilheira seca_morta nativa</tipo_forma_vida><forma_vida_nativa>graminoide</forma_vida_nativa><forma_vida_seca_morta>graminoide</forma_vida_seca_morta><uuid>3b77a511-3aae-4e97-a454-0c151824075d</uuid></registro><registro><ponto_amostral>3</ponto_amostral><ponto_metro>1</ponto_metro><ponto_metro_count /><tipo_forma_vida>serrapilheira seca_morta nativa</tipo_forma_vida><forma_vida_nativa>graminoide</forma_vida_nativa><forma_vida_seca_morta>graminoide</forma_vida_seca_morta><uuid>6a1583cc-f3da-4381-b36f-9ad88fecd962</uuid></registro><registro><ponto_amostral>4</ponto_amostral><ponto_metro>1.5</ponto_metro><ponto_metro_count /><tipo_forma_vida>serrapilheira seca_morta nativa</tipo_forma_vida><forma_vida_nativa>graminoide</forma_vida_nativa><forma_vida_seca_morta>graminoide</forma_vida_seca_morta><uuid>01287477-f496-4d3a-9e62-4f44ac4f1268</uuid></registro><registro><ponto_amostral>5</ponto_amostral><ponto_metro>2</ponto_metro><ponto_metro_count /><tipo_forma_vida>serrapilheira seca_morta nativa</tipo_forma_vida><forma_vida_nativa>graminoide</forma_vida_nativa><forma_vida_seca_morta>graminoide</forma_vida_seca_morta><uuid>f8ecc72f-2cb1-4223-9a63-ba5888bf6014</uuid></registro><registro><ponto_amostral>6</ponto_amostral><ponto_metro>2.5</ponto_metro><ponto_metro_count /><tipo_forma_vida>serrapilheira seca_morta nativa</tipo_forma_vida><forma_vida_nativa>graminoide</forma_vida_nativa><forma_vida_seca_morta>graminoide</forma_vida_seca_morta><uuid>33b8c9a7-724f-43de-b3ba-c4d568ae92a2</uuid></registro><registro><ponto_amostral>7</ponto_amostral><ponto_metro>3</ponto_metro><ponto_metro_count /><tipo_forma_vida>serrapilheira seca_morta nativa</tipo_forma_vida><forma_vida_nativa>graminoide</forma_vida_nativa><forma_vida_seca_morta>graminoide</forma_vida_seca_morta><uuid>163959e4-d3f4-4648-9834-d1f42ee2756a</uuid></registro><registro><ponto_amostral>8</ponto_amostral><ponto_metro>3.5</ponto_metro><ponto_metro_count /><tipo_forma_vida>serrapilheira seca_morta nativa</tipo_forma_vida><forma_vida_nativa>graminoide</forma_vida_nativa><forma_vida_seca_morta>graminoide</forma_vida_seca_morta><uuid>e43ef551-8212-41ac-a206-a8a746563999</uuid></registro><registro><ponto_amostral>9</ponto_amostral><ponto_metro>4</ponto_metro><ponto_metro_count /><tipo_forma_vida>serrapilheira seca_morta nativa</tipo_forma_vida><forma_vida_nativa>graminoide</forma_vida_nativa><forma_vida_seca_morta>graminoide</forma_vida_seca_morta><uuid>23981a7e-359c-4bca-a4ff-d6246aaac152</uuid></registro><registro><ponto_amostral>10</ponto_amostral><ponto_metro>4.5</ponto_metro><ponto_metro_count /><tipo_forma_vida>serrapilheira seca_morta nativa</tipo_forma_vida><forma_vida_nativa>graminoide</forma_vida_nativa><forma_vida_seca_morta>graminoide</forma_vida_seca_morta><uuid>fe35046e-8286-4bb7-9f16-1e17669bed57</uuid></registro><registro><ponto_amostral>11</ponto_amostral><ponto_metro>5</ponto_metro><ponto_metro_count /><tipo_forma_vida>serrapilheira seca_morta nativa</tipo_forma_vida><forma_vida_nativa>graminoide arbusto_acima</forma_vida_nativa><forma_vida_seca_morta>graminoide</forma_vida_seca_morta><uuid>a8216406-9028-4ad7-aba8-e1b5c77a8566</uuid></registro><registro><ponto_amostral>12</ponto_amostral><ponto_metro>5.5</ponto_metro><ponto_metro_count /><tipo_forma_vida>serrapilheira seca_morta nativa</tipo_forma_vida><forma_vida_nativa>graminoide arbusto_abaixo</forma_vida_nativa><forma_vida_seca_morta>graminoide</forma_vida_seca_morta><uuid>4cab3e67-3b60-4c68-94c3-2799f3254198</uuid></registro><registro><ponto_amostral>13</ponto_amostral><ponto_metro>6</ponto_metro><ponto_metro_count /><tipo_forma_vida>serrapilheira seca_morta nativa</tipo_forma_vida><forma_vida_nativa>graminoide arbusto_acima arbusto_abaixo</forma_vida_nativa><forma_vida_seca_morta>graminoide</forma_vida_seca_morta><uuid>b6ba56b5-81a2-46ed-a390-565b2e277a11</uuid></registro><registro><ponto_amostral>14</ponto_amostral><ponto_metro>6.5</ponto_metro><ponto_metro_count /><tipo_forma_vida>serrapilheira seca_morta nativa</tipo_forma_vida><forma_vida_nativa>graminoide arbusto_acima arbusto_abaixo</forma_vida_nativa><forma_vida_seca_morta>graminoide</forma_vida_seca_morta><uuid>ce264b9d-1c48-4479-aada-3abfcd50c179</uuid></registro><registro><ponto_amostral>15</ponto_amostral><ponto_metro>7</ponto_metro><ponto_metro_count /><tipo_forma_vida>serrapilheira seca_morta nativa</tipo_forma_vida><forma_vida_nativa>graminoide arbusto_abaixo arbusto_acima</forma_vida_nativa><forma_vida_seca_morta>graminoide</forma_vida_seca_morta><uuid>a88fe0f8-f860-4762-bd01-109242509ab3</uuid></registro><registro><ponto_amostral>16</ponto_amostral><ponto_metro>7.5</ponto_metro><ponto_metro_count /><tipo_forma_vida>serrapilheira seca_morta nativa</tipo_forma_vida><forma_vida_nativa>arbusto_abaixo arbusto_acima</forma_vida_nativa><forma_vida_seca_morta>graminoide</forma_vida_seca_morta><uuid>ecdcfee2-b93d-44ba-a904-4e7acaf65f82</uuid></registro><registro><ponto_amostral>17</ponto_amostral><ponto_metro>8</ponto_metro><ponto_metro_count /><tipo_forma_vida>serrapilheira seca_morta nativa</tipo_forma_vida><forma_vida_nativa>arbusto_abaixo arbusto_acima graminoide</forma_vida_nativa><forma_vida_seca_morta>graminoide</forma_vida_seca_morta><uuid>fbb961c3-6647-4d87-a091-34e2a434caa8</uuid></registro><registro><ponto_amostral>18</ponto_amostral><ponto_metro>8.5</ponto_metro><ponto_metro_count /><tipo_forma_vida>serrapilheira seca_morta nativa</tipo_forma_vida><forma_vida_nativa>graminoide arbusto_abaixo arbusto_acima</forma_vida_nativa><forma_vida_seca_morta>graminoide</forma_vida_seca_morta><uuid>e1a1ad32-1c57-4b27-b8da-b48c04b990ef</uuid></registro><registro><ponto_amostral>19</ponto_amostral><ponto_metro>9</ponto_metro><ponto_metro_count /><tipo_forma_vida>serrapilheira seca_morta nativa</tipo_forma_vida><forma_vida_nativa>graminoide arbusto_acima arbusto_abaixo</forma_vida_nativa><forma_vida_seca_morta>graminoide</forma_vida_seca_morta><uuid>b620c5a0-38ed-4d46-84c7-7517259d3eea</uuid></registro><registro><ponto_amostral>20</ponto_amostral><ponto_metro>9.5</ponto_metro><ponto_metro_count /><tipo_forma_vida>serrapilheira seca_morta nativa</tipo_forma_vida><forma_vida_nativa>graminoide</forma_vida_nativa><forma_vida_seca_morta>graminoide</forma_vida_seca_morta><uuid>8aee3edc-629a-40eb-a177-094fdbb3ec3d</uuid></registro><registro><ponto_amostral>21</ponto_amostral><ponto_metro>10</ponto_metro><ponto_metro_count /><tipo_forma_vida>serrapilheira seca_morta nativa</tipo_forma_vida><forma_vida_nativa>graminoide</forma_vida_nativa><forma_vida_seca_morta>graminoide</forma_vida_seca_morta><uuid>a8be5d4c-3b51-499a-a58f-0b698488d1eb</uuid></registro><registro><ponto_amostral>22</ponto_amostral><ponto_metro>10.5</ponto_metro><ponto_metro_count /><tipo_forma_vida>serrapilheira seca_morta nativa</tipo_forma_vida><forma_vida_nativa>graminoide arbusto_abaixo arbusto_acima</forma_vida_nativa><forma_vida_seca_morta>graminoide</forma_vida_seca_morta><uuid>cbad2436-12e0-4e9e-a1cb-bdfb1fcafe01</uuid></registro><registro><ponto_amostral>23</ponto_amostral><ponto_metro>11</ponto_metro><ponto_metro_count /><tipo_forma_vida>serrapilheira seca_morta nativa</tipo_forma_vida><forma_vida_nativa>graminoide arbusto_abaixo arbusto_acima</forma_vida_nativa><forma_vida_seca_morta>graminoide</forma_vida_seca_morta><uuid>eba72836-87ad-4360-a3f2-f1a988266796</uuid></registro><registro><ponto_amostral>24</ponto_amostral><ponto_metro>11.5</ponto_metro><ponto_metro_count /><tipo_forma_vida>serrapilheira seca_morta nativa</tipo_forma_vida><forma_vida_nativa>arbusto_abaixo arbusto_acima</forma_vida_nativa><forma_vida_seca_morta>graminoide</forma_vida_seca_morta><uuid>43f6859f-5c90-4299-8fc1-a1131eac1b5b</uuid></registro><registro><ponto_amostral>25</ponto_amostral><ponto_metro>12</ponto_metro><ponto_metro_count /><tipo_forma_vida>serrapilheira seca_morta nativa</tipo_forma_vida><forma_vida_nativa>graminoide arbusto_abaixo arbusto_acima</forma_vida_nativa><forma_vida_seca_morta>graminoide</forma_vida_seca_morta><uuid>b3c1b19c-bd42-4438-a72c-e979d3e2276d</uuid></registro><registro><ponto_amostral>26</ponto_amostral><ponto_metro>12.5</ponto_metro><ponto_metro_count /><tipo_forma_vida>serrapilheira seca_morta nativa</tipo_forma_vida><forma_vida_nativa>graminoide arbusto_abaixo arbusto_acima</forma_vida_nativa><forma_vida_seca_morta>graminoide</forma_vida_seca_morta><uuid>245c4856-1eab-4b5c-a32b-6f9fb0bce0fa</uuid></registro><registro><ponto_amostral>27</ponto_amostral><ponto_metro>13</ponto_metro><ponto_metro_count /><tipo_forma_vida>serrapilheira seca_morta nativa</tipo_forma_vida><forma_vida_nativa>graminoide arbusto_abaixo arbusto_acima</forma_vida_nativa><forma_vida_seca_morta>graminoide</forma_vida_seca_morta><uuid>4d340912-0bef-4964-85ce-0e2625847258</uuid></registro><registro><ponto_amostral>28</ponto_amostral><ponto_metro>13.5</ponto_metro><ponto_metro_count /><tipo_forma_vida>serrapilheira seca_morta nativa</tipo_forma_vida><forma_vida_nativa>graminoide arbusto_abaixo arbusto_acima</forma_vida_nativa><forma_vida_seca_morta>graminoide</forma_vida_seca_morta><uuid>09eed6ff-da06-47be-88b5-5efc6c0aae96</uuid></registro><registro><ponto_amostral>29</ponto_amostral><ponto_metro>14</ponto_metro><ponto_metro_count /><tipo_forma_vida>serrapilheira seca_morta nativa</tipo_forma_vida><forma_vida_nativa>graminoide</forma_vida_nativa><forma_vida_seca_morta>graminoide</forma_vida_seca_morta><uuid>60cd42a7-3002-49e3-8685-00d0318664e6</uuid></registro><registro><ponto_amostral>30</ponto_amostral><ponto_metro>14.5</ponto_metro><ponto_metro_count /><tipo_forma_vida>serrapilheira seca_morta nativa</tipo_forma_vida><forma_vida_nativa>graminoide</forma_vida_nativa><forma_vida_seca_morta>graminoide</forma_vida_seca_morta><uuid>9a17e8d3-8467-4599-be59-caf6b737657f</uuid></registro><registro><ponto_amostral>31</ponto_amostral><ponto_metro>15</ponto_metro><ponto_metro_count /><tipo_forma_vida>serrapilheira seca_morta nativa</tipo_forma_vida><forma_vida_nativa>graminoide</forma_vida_nativa><forma_vida_seca_morta>graminoide</forma_vida_seca_morta><uuid>383e3eba-7f7e-4e67-887d-69c9a50f7162</uuid></registro><registro><ponto_amostral>32</ponto_amostral><ponto_metro>15.5</ponto_metro><ponto_metro_count /><tipo_forma_vida>serrapilheira seca_morta nativa</tipo_forma_vida><forma_vida_nativa>graminoide</forma_vida_nativa><forma_vida_seca_morta>graminoide</forma_vida_seca_morta><uuid>11cc8fac-f722-4ef5-b746-d52e1f85af2e</uuid></registro><registro><ponto_amostral>33</ponto_amostral><ponto_metro>16</ponto_metro><ponto_metro_count /><tipo_forma_vida>serrapilheira seca_morta nativa</tipo_forma_vida><forma_vida_nativa>graminoide erva_nao_graminoide</forma_vida_nativa><forma_vida_seca_morta>graminoide</forma_vida_seca_morta><uuid>6425cd03-84cf-4b46-a299-9c6c7d2ef97b</uuid></registro><registro><ponto_amostral>34</ponto_amostral><ponto_metro>16.5</ponto_metro><ponto_metro_count /><tipo_forma_vida>serrapilheira seca_morta nativa</tipo_forma_vida><forma_vida_nativa>graminoide lianas</forma_vida_nativa><forma_vida_seca_morta>graminoide</forma_vida_seca_morta><uuid>c0be1b26-c14e-457c-9808-765033049717</uuid></registro><registro><ponto_amostral>35</ponto_amostral><ponto_metro>17</ponto_metro><ponto_metro_count /><tipo_forma_vida>serrapilheira seca_morta nativa</tipo_forma_vida><forma_vida_nativa>graminoide</forma_vida_nativa><forma_vida_seca_morta>graminoide</forma_vida_seca_morta><uuid>65f2094e-06eb-45ec-b170-aa7733996414</uuid></registro><registro><ponto_amostral>36</ponto_amostral><ponto_metro>17.5</ponto_metro><ponto_metro_count /><tipo_forma_vida>serrapilheira seca_morta nativa</tipo_forma_vida><forma_vida_nativa>graminoide</forma_vida_nativa><forma_vida_seca_morta>graminoide</forma_vida_seca_morta><uuid>75b6e6bc-82bd-4113-9888-6a97ffb5cfa0</uuid></registro><registro><ponto_amostral>37</ponto_amostral><ponto_metro>18</ponto_metro><ponto_metro_count /><tipo_forma_vida>serrapilheira seca_morta nativa</tipo_forma_vida><forma_vida_nativa>graminoide lianas</forma_vida_nativa><forma_vida_seca_morta>graminoide</forma_vida_seca_morta><uuid>d62cd8fc-6508-4394-bfa9-6d6d12189fce</uuid></registro><registro><ponto_amostral>38</ponto_amostral><ponto_metro>18.5</ponto_metro><ponto_metro_count /><tipo_forma_vida>serrapilheira seca_morta</tipo_forma_vida><forma_vida_seca_morta>graminoide</forma_vida_seca_morta><uuid>cdac879a-f0c3-4d58-8b67-f0452d1d82ca</uuid></registro><registro><ponto_amostral>39</ponto_amostral><ponto_metro>19</ponto_metro><ponto_metro_count /><tipo_forma_vida>serrapilheira seca_morta nativa</tipo_forma_vida><forma_vida_nativa>graminoide</forma_vida_nativa><forma_vida_seca_morta>graminoide</forma_vida_seca_morta><uuid>0b844774-eacc-4541-8867-4e5abd72d6a0</uuid></registro><registro><ponto_amostral>40</ponto_amostral><ponto_metro>19.5</ponto_metro><ponto_metro_count /><tipo_forma_vida>serrapilheira seca_morta nativa</tipo_forma_vida><forma_vida_nativa>graminoide</forma_vida_nativa><forma_vida_seca_morta>graminoide</forma_vida_seca_morta><uuid>16ff50cd-9509-4032-9710-c85b3abdc2ba</uuid></registro><registro><ponto_amostral>41</ponto_amostral><ponto_metro>20</ponto_metro><ponto_metro_count /><tipo_forma_vida>serrapilheira seca_morta nativa</tipo_forma_vida><forma_vida_nativa>graminoide</forma_vida_nativa><forma_vida_seca_morta>graminoide</forma_vida_seca_morta><uuid>946bcfea-9813-439e-b17a-a45947c2bbca</uuid></registro><registro><ponto_amostral>42</ponto_amostral><ponto_metro>20.5</ponto_metro><ponto_metro_count /><tipo_forma_vida>serrapilheira seca_morta nativa</tipo_forma_vida><forma_vida_nativa>graminoide</forma_vida_nativa><forma_vida_seca_morta>graminoide</forma_vida_seca_morta><uuid>df03f0d9-1130-4c4c-995e-59da5b8b3a96</uuid></registro><registro><ponto_amostral>43</ponto_amostral><ponto_metro>21</ponto_metro><ponto_metro_count /><tipo_forma_vida>serrapilheira seca_morta</tipo_forma_vida><forma_vida_seca_morta>graminoide</forma_vida_seca_morta><uuid>56465d63-4e7a-4e8d-a566-a2807e36774a</uuid></registro><registro><ponto_amostral>44</ponto_amostral><ponto_metro>21.5</ponto_metro><ponto_metro_count /><tipo_forma_vida>serrapilheira seca_morta nativa</tipo_forma_vida><forma_vida_nativa>graminoide</forma_vida_nativa><forma_vida_seca_morta>graminoide</forma_vida_seca_morta><uuid>a6a7e8d4-8ba2-453e-8dfe-e5d0dee4d4b4</uuid></registro><registro><ponto_amostral>45</ponto_amostral><ponto_metro>22</ponto_metro><ponto_metro_count /><tipo_forma_vida>serrapilheira seca_morta nativa</tipo_forma_vida><forma_vida_nativa>graminoide</forma_vida_nativa><forma_vida_seca_morta>graminoide</forma_vida_seca_morta><uuid>5d31f7b0-2581-41c4-8867-eda30757c802</uuid></registro><registro><ponto_amostral>46</ponto_amostral><ponto_metro>22.5</ponto_metro><ponto_metro_count /><tipo_forma_vida>serrapilheira seca_morta nativa</tipo_forma_vida><forma_vida_nativa>graminoide</forma_vida_nativa><forma_vida_seca_morta>graminoide</forma_vida_seca_morta><uuid>b7f9915a-823d-4c80-a785-96788746a829</uuid></registro><registro><ponto_amostral>47</ponto_amostral><ponto_metro>23</ponto_metro><ponto_metro_count /><tipo_forma_vida>serrapilheira seca_morta nativa</tipo_forma_vida><forma_vida_nativa>graminoide</forma_vida_nativa><forma_vida_seca_morta>graminoide</forma_vida_seca_morta><uuid>e9703d33-6bb5-42c4-a46b-63cfe779c823</uuid></registro><registro><ponto_amostral>48</ponto_amostral><ponto_metro>23.5</ponto_metro><ponto_metro_count /><tipo_forma_vida>serrapilheira seca_morta nativa</tipo_forma_vida><forma_vida_nativa>graminoide arbusto_abaixo</forma_vida_nativa><forma_vida_seca_morta>graminoide</forma_vida_seca_morta><uuid>29382ef3-bf2d-4c78-a535-0e78c841a40f</uuid></registro><registro><ponto_amostral>49</ponto_amostral><ponto_metro>24</ponto_metro><ponto_metro_count /><tipo_forma_vida>serrapilheira seca_morta nativa</tipo_forma_vida><forma_vida_nativa>graminoide arvore_acima</forma_vida_nativa><forma_vida_seca_morta>graminoide</forma_vida_seca_morta><uuid>c9304570-3baa-4ffe-9de7-855270a35f9d</uuid></registro><registro><ponto_amostral>50</ponto_amostral><ponto_metro>24.5</ponto_metro><ponto_metro_count /><tipo_forma_vida>serrapilheira seca_morta nativa</tipo_forma_vida><forma_vida_nativa>graminoide</forma_vida_nativa><forma_vida_seca_morta>graminoide</forma_vida_seca_morta><uuid>7e4b2b9a-5062-46f1-9089-a5542a9c41fb</uuid></registro><registro><ponto_amostral>51</ponto_amostral><ponto_metro>25</ponto_metro><ponto_metro_count /><tipo_forma_vida>serrapilheira seca_morta nativa</tipo_forma_vida><forma_vida_nativa>arvore_acima</forma_vida_nativa><forma_vida_seca_morta>graminoide</forma_vida_seca_morta><uuid>42e623ba-4ed2-4f61-9067-6362837028f3</uuid></registro><registro><ponto_amostral>52</ponto_amostral><ponto_metro>25.5</ponto_metro><ponto_metro_count /><tipo_forma_vida>serrapilheira seca_morta nativa</tipo_forma_vida><forma_vida_nativa>lianas arvore_acima</forma_vida_nativa><forma_vida_seca_morta>graminoide</forma_vida_seca_morta><uuid>4d420bc5-72a0-4895-b0ba-a4c2500c8c54</uuid></registro><registro><ponto_amostral>53</ponto_amostral><ponto_metro>26</ponto_metro><ponto_metro_count /><tipo_forma_vida>serrapilheira seca_morta nativa</tipo_forma_vida><forma_vida_nativa>graminoide arvore_acima</forma_vida_nativa><forma_vida_seca_morta>graminoide</forma_vida_seca_morta><uuid>36a2399d-4dda-423f-9f1c-78d0b08a9563</uuid></registro><registro><ponto_amostral>54</ponto_amostral><ponto_metro>26.5</ponto_metro><ponto_metro_count /><tipo_forma_vida>serrapilheira seca_morta nativa</tipo_forma_vida><forma_vida_nativa>graminoide arvore_acima</forma_vida_nativa><forma_vida_seca_morta>graminoide</forma_vida_seca_morta><uuid>dbe0101b-8d01-405e-b601-79517bcad829</uuid></registro><registro><ponto_amostral>55</ponto_amostral><ponto_metro>27</ponto_metro><ponto_metro_count /><tipo_forma_vida>serrapilheira seca_morta nativa</tipo_forma_vida><forma_vida_nativa>arvore_acima</forma_vida_nativa><forma_vida_seca_morta>graminoide</forma_vida_seca_morta><uuid>cfb58bba-bf1b-4670-af85-10638a1ec3da</uuid></registro><registro><ponto_amostral>56</ponto_amostral><ponto_metro>27.5</ponto_metro><ponto_metro_count /><tipo_forma_vida>serrapilheira seca_morta nativa</tipo_forma_vida><forma_vida_nativa>graminoide arvore_acima</forma_vida_nativa><forma_vida_seca_morta>graminoide</forma_vida_seca_morta><uuid>d52ac3c6-1836-4c7a-af48-29aae602fbb2</uuid></registro><registro><ponto_amostral>57</ponto_amostral><ponto_metro>28</ponto_metro><ponto_metro_count /><tipo_forma_vida>serrapilheira seca_morta</tipo_forma_vida><forma_vida_seca_morta>graminoide arvore_acima</forma_vida_seca_morta><uuid>6341baa0-2705-47da-9371-2a522bae0b8b</uuid></registro><registro><ponto_amostral>58</ponto_amostral><ponto_metro>28.5</ponto_metro><ponto_metro_count /><tipo_forma_vida>serrapilheira seca_morta nativa</tipo_forma_vida><forma_vida_nativa>graminoide lianas</forma_vida_nativa><forma_vida_seca_morta>graminoide arvore_acima</forma_vida_seca_morta><uuid>f88756bb-70dc-487b-adfa-ed8e077ab52a</uuid></registro><registro><ponto_amostral>59</ponto_amostral><ponto_metro>29</ponto_metro><ponto_metro_count /><tipo_forma_vida>serrapilheira seca_morta nativa</tipo_forma_vida><forma_vida_nativa>lianas graminoide</forma_vida_nativa><forma_vida_seca_morta>graminoide arvore_acima</forma_vida_seca_morta><uuid>e821242c-a504-4859-8955-ea4f42c72289</uuid></registro><registro><ponto_amostral>60</ponto_amostral><ponto_metro>29.5</ponto_metro><ponto_metro_count /><tipo_forma_vida>serrapilheira seca_morta nativa</tipo_forma_vida><forma_vida_nativa>graminoide lianas</forma_vida_nativa><forma_vida_seca_morta>graminoide</forma_vida_seca_morta><uuid>e9d290ec-f642-4282-9c3c-d931d76b44d3</uuid></registro><registro><ponto_amostral>61</ponto_amostral><ponto_metro>30</ponto_metro><ponto_metro_count /><tipo_forma_vida>serrapilheira seca_morta</tipo_forma_vida><forma_vida_seca_morta>graminoide</forma_vida_seca_morta><uuid>b37029ea-2047-49d3-a37e-19d9a217227e</uuid></registro><registro><ponto_amostral>62</ponto_amostral><ponto_metro>30.5</ponto_metro><ponto_metro_count /><tipo_forma_vida>serrapilheira seca_morta nativa</tipo_forma_vida><forma_vida_nativa>graminoide</forma_vida_nativa><forma_vida_seca_morta>graminoide</forma_vida_seca_morta><uuid>237176bf-e127-4063-9937-4ad3d0b1a7cd</uuid></registro><registro><ponto_amostral>63</ponto_amostral><ponto_metro>31</ponto_metro><ponto_metro_count /><tipo_forma_vida>seca_morta nativa serrapilheira</tipo_forma_vida><forma_vida_nativa>graminoide</forma_vida_nativa><forma_vida_seca_morta>graminoide</forma_vida_seca_morta><uuid>13bb881c-a5d0-43d8-bef1-5dc2c2888148</uuid></registro><registro><ponto_amostral>64</ponto_amostral><ponto_metro>31.5</ponto_metro><ponto_metro_count /><tipo_forma_vida>serrapilheira seca_morta nativa</tipo_forma_vida><forma_vida_nativa>lianas graminoide</forma_vida_nativa><forma_vida_seca_morta>graminoide</forma_vida_seca_morta><uuid>088c820d-f610-4df0-ac38-0d72e204ecc8</uuid></registro><registro><ponto_amostral>65</ponto_amostral><ponto_metro>32</ponto_metro><ponto_metro_count /><tipo_forma_vida>serrapilheira seca_morta nativa</tipo_forma_vida><forma_vida_nativa>graminoide</forma_vida_nativa><forma_vida_seca_morta>graminoide</forma_vida_seca_morta><uuid>736ce389-10ae-4b08-a4b3-94efd4d4b500</uuid></registro><registro><ponto_amostral>66</ponto_amostral><ponto_metro>32.5</ponto_metro><ponto_metro_count /><tipo_forma_vida>serrapilheira seca_morta nativa</tipo_forma_vida><forma_vida_nativa>graminoide</forma_vida_nativa><forma_vida_seca_morta>graminoide</forma_vida_seca_morta><uuid>bc442e92-3b1d-4add-ba86-394e70639184</uuid></registro><registro><ponto_amostral>67</ponto_amostral><ponto_metro>33</ponto_metro><ponto_metro_count /><tipo_forma_vida>serrapilheira seca_morta nativa</tipo_forma_vida><forma_vida_nativa>graminoide arvore_acima</forma_vida_nativa><forma_vida_seca_morta>graminoide</forma_vida_seca_morta><uuid>af8196d3-de2f-4f4c-a484-bdfdb3c7a85a</uuid></registro><registro><ponto_amostral>68</ponto_amostral><ponto_metro>33.5</ponto_metro><ponto_metro_count /><tipo_forma_vida>serrapilheira seca_morta nativa</tipo_forma_vida><forma_vida_nativa>lianas arvore_acima</forma_vida_nativa><forma_vida_seca_morta>graminoide</forma_vida_seca_morta><uuid>9e49ec7c-f8d3-4bc4-816b-804e3de2654f</uuid></registro><registro><ponto_amostral>69</ponto_amostral><ponto_metro>34</ponto_metro><ponto_metro_count /><tipo_forma_vida>serrapilheira seca_morta nativa</tipo_forma_vida><forma_vida_nativa>graminoide arvore_acima</forma_vida_nativa><forma_vida_seca_morta>graminoide</forma_vida_seca_morta><uuid>e7dc1338-1283-4304-a7b7-7d104ce75ecc</uuid></registro><registro><ponto_amostral>70</ponto_amostral><ponto_metro>34.5</ponto_metro><ponto_metro_count /><tipo_forma_vida>serrapilheira seca_morta nativa</tipo_forma_vida><forma_vida_nativa>arvore_acima graminoide</forma_vida_nativa><forma_vida_seca_morta>graminoide</forma_vida_seca_morta><uuid>7d22f828-fd7c-4aad-b13d-415a07dc4819</uuid></registro><registro><ponto_amostral>71</ponto_amostral><ponto_metro>35</ponto_metro><ponto_metro_count /><tipo_forma_vida>serrapilheira seca_morta nativa</tipo_forma_vida><forma_vida_nativa>graminoide arvore_acima</forma_vida_nativa><forma_vida_seca_morta>graminoide</forma_vida_seca_morta><uuid>990b647e-d4ea-49c2-89b4-afac05b121b1</uuid></registro><registro><ponto_amostral>72</ponto_amostral><ponto_metro>35.5</ponto_metro><ponto_metro_count /><tipo_forma_vida>serrapilheira seca_morta nativa</tipo_forma_vida><forma_vida_nativa>arvore_acima lianas</forma_vida_nativa><forma_vida_seca_morta>graminoide</forma_vida_seca_morta><uuid>018fbe25-baf3-4269-b1c7-8bae65051f6a</uuid></registro><registro><ponto_amostral>73</ponto_amostral><ponto_metro>36</ponto_metro><ponto_metro_count /><tipo_forma_vida>serrapilheira seca_morta nativa</tipo_forma_vida><forma_vida_nativa>arvore_acima</forma_vida_nativa><forma_vida_seca_morta>graminoide</forma_vida_seca_morta><uuid>cf84f4bf-be8e-42a0-932e-a081df3be6e0</uuid></registro><registro><ponto_amostral>74</ponto_amostral><ponto_metro>36.5</ponto_metro><ponto_metro_count /><tipo_forma_vida>serrapilheira seca_morta</tipo_forma_vida><forma_vida_seca_morta>graminoide</forma_vida_seca_morta><uuid>4fb862a7-1b90-410e-bc46-f3982d7a909b</uuid></registro><registro><ponto_amostral>75</ponto_amostral><ponto_metro>37</ponto_metro><ponto_metro_count /><tipo_forma_vida>serrapilheira seca_morta nativa</tipo_forma_vida><forma_vida_nativa>graminoide</forma_vida_nativa><forma_vida_seca_morta>graminoide</forma_vida_seca_morta><uuid>a9e4e2e7-6a97-44a7-8de9-fe723202bb95</uuid></registro><registro><ponto_amostral>76</ponto_amostral><ponto_metro>37.5</ponto_metro><ponto_metro_count /><tipo_forma_vida>serrapilheira seca_morta nativa</tipo_forma_vida><forma_vida_nativa>graminoide</forma_vida_nativa><forma_vida_seca_morta>graminoide</forma_vida_seca_morta><uuid>891b1b60-2355-43c8-9cfa-684deef42e9d</uuid></registro><registro><ponto_amostral>77</ponto_amostral><ponto_metro>38</ponto_metro><ponto_metro_count /><tipo_forma_vida>serrapilheira seca_morta nativa</tipo_forma_vida><forma_vida_nativa>graminoide</forma_vida_nativa><forma_vida_seca_morta>graminoide</forma_vida_seca_morta><uuid>3e0447c3-189b-4ca7-86c7-16422804b34d</uuid></registro><registro><ponto_amostral>78</ponto_amostral><ponto_metro>38.5</ponto_metro><ponto_metro_count /><tipo_forma_vida>serrapilheira seca_morta nativa</tipo_forma_vida><forma_vida_nativa>graminoide</forma_vida_nativa><forma_vida_seca_morta>graminoide</forma_vida_seca_morta><uuid>bfe10b42-88f5-43d0-91f7-b50dca288861</uuid></registro><registro><ponto_amostral>79</ponto_amostral><ponto_metro>39</ponto_metro><ponto_metro_count /><tipo_forma_vida>serrapilheira seca_morta nativa</tipo_forma_vida><forma_vida_nativa>graminoide</forma_vida_nativa><forma_vida_seca_morta>graminoide</forma_vida_seca_morta><uuid>855ff1d8-d122-4ebb-8703-c24a7c34f92c</uuid></registro><registro><ponto_amostral>80</ponto_amostral><ponto_metro>39.5</ponto_metro><ponto_metro_count /><tipo_forma_vida>serrapilheira seca_morta nativa</tipo_forma_vida><forma_vida_nativa>graminoide</forma_vida_nativa><forma_vida_seca_morta>graminoide</forma_vida_seca_morta><uuid>aa74aa3b-316b-45f8-a3f2-dece0db2b3d8</uuid></registro><registro><ponto_amostral>81</ponto_amostral><ponto_metro>40</ponto_metro><ponto_metro_count /><tipo_forma_vida>serrapilheira seca_morta nativa</tipo_forma_vida><forma_vida_nativa>graminoide arbusto_abaixo</forma_vida_nativa><forma_vida_seca_morta>graminoide</forma_vida_seca_morta><uuid>ec24f7b3-10a6-4b06-8d1a-19afed1bcd17</uuid></registro><registro><ponto_amostral>82</ponto_amostral><ponto_metro>40.5</ponto_metro><ponto_metro_count /><tipo_forma_vida>serrapilheira seca_morta nativa</tipo_forma_vida><forma_vida_nativa>graminoide arbusto_abaixo</forma_vida_nativa><forma_vida_seca_morta>graminoide</forma_vida_seca_morta><uuid>f447e27b-54eb-4c17-b1a5-3a4e0c98acca</uuid></registro><registro><ponto_amostral>83</ponto_amostral><ponto_metro>41</ponto_metro><ponto_metro_count /><tipo_forma_vida>serrapilheira seca_morta nativa</tipo_forma_vida><forma_vida_nativa>graminoide</forma_vida_nativa><forma_vida_seca_morta>graminoide</forma_vida_seca_morta><uuid>2129c989-d3a2-4b26-bb4e-17903dd59af6</uuid></registro><registro><ponto_amostral>84</ponto_amostral><ponto_metro>41.5</ponto_metro><ponto_metro_count /><tipo_forma_vida>serrapilheira seca_morta nativa</tipo_forma_vida><forma_vida_nativa>graminoide</forma_vida_nativa><forma_vida_seca_morta>graminoide</forma_vida_seca_morta><uuid>741aed8d-48a8-443e-baaa-91901ec5f99a</uuid></registro><registro><ponto_amostral>85</ponto_amostral><ponto_metro>42</ponto_metro><ponto_metro_count /><tipo_forma_vida>serrapilheira seca_morta nativa</tipo_forma_vida><forma_vida_nativa>graminoide arbusto_acima arbusto_abaixo</forma_vida_nativa><forma_vida_seca_morta>graminoide</forma_vida_seca_morta><uuid>c378185d-481c-428b-a756-46803dad1668</uuid></registro><registro><ponto_amostral>86</ponto_amostral><ponto_metro>42.5</ponto_metro><ponto_metro_count /><tipo_forma_vida>serrapilheira seca_morta nativa</tipo_forma_vida><forma_vida_nativa>arbusto_abaixo graminoide</forma_vida_nativa><forma_vida_seca_morta>graminoide</forma_vida_seca_morta><uuid>5aa50c2d-3d34-4cc5-9ae7-6a100b0c4bc3</uuid></registro><registro><ponto_amostral>87</ponto_amostral><ponto_metro>43</ponto_metro><ponto_metro_count /><tipo_forma_vida>serrapilheira seca_morta nativa</tipo_forma_vida><forma_vida_nativa>graminoide erva_nao_graminoide arbusto_acima</forma_vida_nativa><forma_vida_seca_morta>graminoide</forma_vida_seca_morta><uuid>b04cc9cb-abb2-4081-881a-53cd4d7090e4</uuid></registro><registro><ponto_amostral>88</ponto_amostral><ponto_metro>43.5</ponto_metro><ponto_metro_count /><tipo_forma_vida>serrapilheira seca_morta nativa</tipo_forma_vida><forma_vida_nativa>graminoide arvore_acima</forma_vida_nativa><forma_vida_seca_morta>graminoide</forma_vida_seca_morta><uuid>19e65af6-9fa3-4ff4-9128-9627b1b3caae</uuid></registro><registro><ponto_amostral>89</ponto_amostral><ponto_metro>44</ponto_metro><ponto_metro_count /><tipo_forma_vida>serrapilheira seca_morta nativa</tipo_forma_vida><forma_vida_nativa>graminoide</forma_vida_nativa><forma_vida_seca_morta>graminoide</forma_vida_seca_morta><uuid>cb69c7ed-897d-4c10-967d-750452280e2c</uuid></registro><registro><ponto_amostral>90</ponto_amostral><ponto_metro>44.5</ponto_metro><ponto_metro_count /><tipo_forma_vida>serrapilheira seca_morta nativa</tipo_forma_vida><forma_vida_nativa>arbusto_acima graminoide</forma_vida_nativa><forma_vida_seca_morta>graminoide</forma_vida_seca_morta><uuid>cacfd18b-9773-49c5-8d1d-90e3cb9c2783</uuid></registro><registro><ponto_amostral>91</ponto_amostral><ponto_metro>45</ponto_metro><ponto_metro_count /><tipo_forma_vida>serrapilheira seca_morta</tipo_forma_vida><forma_vida_seca_morta>graminoide</forma_vida_seca_morta><uuid>5fdbfe4b-8c1f-4703-b06b-e56a5c4d24e8</uuid></registro><registro><ponto_amostral>92</ponto_amostral><ponto_metro>45.5</ponto_metro><ponto_metro_count /><tipo_forma_vida>serrapilheira seca_morta nativa</tipo_forma_vida><forma_vida_nativa>graminoide</forma_vida_nativa><forma_vida_seca_morta>graminoide</forma_vida_seca_morta><uuid>b641021e-4fe3-4928-8156-2cf20982be73</uuid></registro><registro><ponto_amostral>93</ponto_amostral><ponto_metro>46</ponto_metro><ponto_metro_count /><tipo_forma_vida>serrapilheira seca_morta nativa</tipo_forma_vida><forma_vida_nativa>arbusto_acima graminoide</forma_vida_nativa><forma_vida_seca_morta>graminoide</forma_vida_seca_morta><uuid>a2fe4a4d-a887-43bc-9a1e-aa83373afca2</uuid></registro><registro><ponto_amostral>94</ponto_amostral><ponto_metro>46.5</ponto_metro><ponto_metro_count /><tipo_forma_vida>serrapilheira seca_morta nativa</tipo_forma_vida><forma_vida_nativa>arbusto_acima</forma_vida_nativa><forma_vida_seca_morta>graminoide</forma_vida_seca_morta><uuid>4c733094-b797-4418-adf1-ff1cfa1bc9db</uuid></registro><registro><ponto_amostral>95</ponto_amostral><ponto_metro>47</ponto_metro><ponto_metro_count /><tipo_forma_vida>serrapilheira seca_morta</tipo_forma_vida><forma_vida_seca_morta>graminoide</forma_vida_seca_morta><uuid>0fb22732-5442-4109-98c7-ff22c0e9fb9c</uuid></registro><registro><ponto_amostral>96</ponto_amostral><ponto_metro>47.5</ponto_metro><ponto_metro_count /><tipo_forma_vida>serrapilheira seca_morta nativa</tipo_forma_vida><forma_vida_nativa>arbusto_acima</forma_vida_nativa><forma_vida_seca_morta>graminoide</forma_vida_seca_morta><uuid>2b52a14f-00dc-4b52-ad3c-28505576c29f</uuid></registro><registro><ponto_amostral>97</ponto_amostral><ponto_metro>48</ponto_metro><ponto_metro_count /><tipo_forma_vida>serrapilheira seca_morta nativa</tipo_forma_vida><forma_vida_nativa>graminoide</forma_vida_nativa><forma_vida_seca_morta>graminoide</forma_vida_seca_morta><uuid>3e4cb5be-900c-46b0-8a3b-715dab00491f</uuid></registro><registro><ponto_amostral>98</ponto_amostral><ponto_metro>48.5</ponto_metro><ponto_metro_count /><tipo_forma_vida>serrapilheira seca_morta nativa</tipo_forma_vida><forma_vida_nativa>arbusto_acima graminoide</forma_vida_nativa><forma_vida_seca_morta>graminoide</forma_vida_seca_morta><uuid>b1b396a6-acc9-4b76-b2bd-a34a9fa05d27</uuid></registro><registro><ponto_amostral>99</ponto_amostral><ponto_metro>49</ponto_metro><ponto_metro_count /><tipo_forma_vida>serrapilheira seca_morta</tipo_forma_vida><forma_vida_seca_morta>graminoide</forma_vida_seca_morta><uuid>cdf1bb92-7cd5-443e-a19f-b80a66ef8165</uuid></registro><registro><ponto_amostral>100</ponto_amostral><ponto_metro>49.5</ponto_metro><ponto_metro_count /><tipo_forma_vida>serrapilheira seca_morta nativa</tipo_forma_vida><forma_vida_nativa>graminoide</forma_vida_nativa><forma_vida_seca_morta>graminoide</forma_vida_seca_morta><uuid>a294a9ad-c214-41dd-bd87-7ad1dabeede5</uuid></registro><registro><ponto_amostral>101</ponto_amostral><ponto_metro>50</ponto_metro><ponto_metro_count /><tipo_forma_vida>serrapilheira seca_morta nativa</tipo_forma_vida><forma_vida_nativa>graminoide</forma_vida_nativa><forma_vida_seca_morta>graminoide</forma_vida_seca_morta><uuid>76d08935-f753-45d7-a510-9a95ab30f557</uuid></registro><ponto_fim_transecto>-12.3079649 -63.3874093 162.26123046875 4.915</ponto_fim_transecto><foto_ponto_final>1698414474473.jpg</foto_ponto_final></amostragem><uuid>b8f7421e-eca2-4e1f-a9d3-197d36f7cdb3</uuid><endtime>2023-10-27T10:53:17.957-04:00</endtime><meta><instanceID>uuid:634cdc75-d602-4f1e-9e96-03a82d25310a</instanceID></meta></PLANTASHERBACEASELENHOSAS_CAMPSAV_05MAI23>